[
  {
    "demandRid": "5b891dacbd60509684b9e7cc",
    "meterMRID": "5b89180b6ec7a3373fdc8dcd",
    "serviceType": "1+undefined",
    "requestDate": "2016-12-06",
    "slaPriority": 27,
    "responseDeadline": "2017-07-01",
    "responseDate": "2015-12-24",
    "status": "OK",
    "failureCode": "failure +0"
  },
  {
    "demandRid": "5b891dacd4b454b2f77e80b0",
    "meterMRID": "5b89180ba15bb86b9d0d91cd",
    "serviceType": "1+undefined",
    "requestDate": "2014-11-28",
    "slaPriority": 1,
    "responseDeadline": "2018-07-11",
    "responseDate": "2016-12-19",
    "status": "SUCCESS",
    "failureCode": "failure +0"
  },
  {
    "demandRid": "5b891dacf9a1dad4bc06f275",
    "meterMRID": "5b89180b6ec7a3373fdc8dcd",
    "serviceType": "1+undefined",
    "requestDate": "2014-08-31",
    "slaPriority": 27,
    "responseDeadline": "2014-07-03",
    "responseDate": "2014-11-20",
    "status": "FAIL",
    "failureCode": "failure +0"
  },
  {
    "demandRid": "5b891dacef135fc13d1f376f",
    "meterMRID": "5b89180b4ffa88ba3d210819",
    "serviceType": "1+undefined",
    "requestDate": "2017-11-08",
    "slaPriority": 27,
    "responseDeadline": "2017-10-02",
    "responseDate": "2018-06-12",
    "status": "SUCCESS",
    "failureCode": "failure +100"
  },
  {
    "demandRid": "5b891dac7a6047a6ab8f46cc",
    "meterMRID": "5b89180b54f5139639a2cbd7",
    "serviceType": "1+undefined",
    "requestDate": "2015-12-17",
    "slaPriority": 27,
    "responseDeadline": "2016-07-26",
    "responseDate": "2015-06-17",
    "status": "SUCCESS",
    "failureCode": "failure +0"
  },
  {
    "demandRid": "5b891dacd672fa52e153f2fd",
    "meterMRID": "5b89180b4dea33c30a1d4949",
    "serviceType": "1+undefined",
    "requestDate": "2016-06-08",
    "slaPriority": 27,
    "responseDeadline": "2016-10-05",
    "responseDate": "2018-06-06",
    "status": "FAIL",
    "failureCode": "failure +0"
  },
  {
    "demandRid": "5b891dac376bb29d51f75897",
    "meterMRID": "5b89180b44c660797d20b1bd",
    "serviceType": "1+undefined",
    "requestDate": "2017-04-11",
    "slaPriority": 9,
    "responseDeadline": "2017-01-02",
    "responseDate": "2015-04-01",
    "status": "SUCCESS",
    "failureCode": "failure +0"
  },
  {
    "demandRid": "5b891dac1b1af17e8f1924ad",
    "meterMRID": "5b89180b6ec7a3373fdc8dcd",
    "serviceType": "1+undefined",
    "requestDate": "2015-04-28",
    "slaPriority": 27,
    "responseDeadline": "2014-04-10",
    "responseDate": "2018-04-22",
    "status": "FAIL",
    "failureCode": "failure +0"
  },
  {
    "demandRid": "5b891dac29df9a76da239734",
    "meterMRID": "5b89180b54f5139639a2cbd7",
    "serviceType": "1+undefined",
    "requestDate": "2016-09-15",
    "slaPriority": 1,
    "responseDeadline": "2015-03-31",
    "responseDate": "2015-11-03",
    "status": "SUCCESS",
    "failureCode": "failure +0"
  },
  {
    "demandRid": "5b891dac043d29bb8aec862c",
    "meterMRID": "5b89180ba15bb86b9d0d91cd",
    "serviceType": "1+undefined",
    "requestDate": "2015-02-08",
    "slaPriority": 1,
    "responseDeadline": "2017-06-04",
    "responseDate": "2018-08-31",
    "status": "SUCCESS",
    "failureCode": "failure +0"
  },
  {
    "demandRid": "5b891dacf0e4b9ea9f32e1d6",
    "meterMRID": "5b89180b4ffa88ba3d210819",
    "serviceType": "1+undefined",
    "requestDate": "2015-08-01",
    "slaPriority": 9,
    "responseDeadline": "2016-02-04",
    "responseDate": "2017-07-05",
    "status": "OK",
    "failureCode": "failure +100"
  },
  {
    "demandRid": "5b891dacb29181368785e0f5",
    "meterMRID": "5b89180b44c660797d20b1bd",
    "serviceType": "1+undefined",
    "requestDate": "2015-03-01",
    "slaPriority": 9,
    "responseDeadline": "2014-03-11",
    "responseDate": "2017-10-10",
    "status": "OK",
    "failureCode": "failure +100"
  },
  {
    "demandRid": "5b891dac3923a1c0d380f7d3",
    "meterMRID": "5b89180be32a0233adbccaa8",
    "serviceType": "1+undefined",
    "requestDate": "2016-04-19",
    "slaPriority": 27,
    "responseDeadline": "2017-06-21",
    "responseDate": "2014-01-10",
    "status": "OK",
    "failureCode": "failure +100"
  },
  {
    "demandRid": "5b891dacf97897f9a54c2107",
    "meterMRID": "5b89180b54f5139639a2cbd7",
    "serviceType": "1+undefined",
    "requestDate": "2015-10-06",
    "slaPriority": 1,
    "responseDeadline": "2016-02-05",
    "responseDate": "2015-04-30",
    "status": "FAIL",
    "failureCode": "failure +0"
  },
  {
    "demandRid": "5b891dac62829b2999095c08",
    "meterMRID": "5b89180b4ffa88ba3d210819",
    "serviceType": "1+undefined",
    "requestDate": "2015-05-28",
    "slaPriority": 9,
    "responseDeadline": "2015-08-26",
    "responseDate": "2018-05-02",
    "status": "SUCCESS",
    "failureCode": "failure +100"
  },
  {
    "demandRid": "5b891dac39ef1d84bb3ce87c",
    "meterMRID": "5b89180be32a0233adbccaa8",
    "serviceType": "1+undefined",
    "requestDate": "2016-03-13",
    "slaPriority": 9,
    "responseDeadline": "2015-01-18",
    "responseDate": "2014-03-31",
    "status": "FAIL",
    "failureCode": "failure +100"
  },
  {
    "demandRid": "5b891dacbbba8d51067d279e",
    "meterMRID": "5b89180bf90f9c23ffdbfc19",
    "serviceType": "1+undefined",
    "requestDate": "2017-09-25",
    "slaPriority": 27,
    "responseDeadline": "2015-02-04",
    "responseDate": "2017-07-25",
    "status": "FAIL",
    "failureCode": "failure +100"
  },
  {
    "demandRid": "5b891dac0602a8970e175cd9",
    "meterMRID": "5b89180b4ffa88ba3d210819",
    "serviceType": "1+undefined",
    "requestDate": "2014-01-16",
    "slaPriority": 9,
    "responseDeadline": "2015-04-04",
    "responseDate": "2014-12-16",
    "status": "FAIL",
    "failureCode": "failure +100"
  },
  {
    "demandRid": "5b891dac6374ffc0abeb16af",
    "meterMRID": "5b89180b4ffa88ba3d210819",
    "serviceType": "1+undefined",
    "requestDate": "2018-02-25",
    "slaPriority": 9,
    "responseDeadline": "2015-11-01",
    "responseDate": "2018-08-22",
    "status": "FAIL",
    "failureCode": "failure +100"
  },
  {
    "demandRid": "5b891dac164d13ef91a7515b",
    "meterMRID": "5b89180be32a0233adbccaa8",
    "serviceType": "1+undefined",
    "requestDate": "2015-06-30",
    "slaPriority": 1,
    "responseDeadline": "2017-01-09",
    "responseDate": "2014-04-10",
    "status": "FAIL",
    "failureCode": "failure +0"
  },
  {
    "demandRid": "5b891dac9cdc6c9ffce9ea3e",
    "meterMRID": "5b89180b44c660797d20b1bd",
    "serviceType": "1+undefined",
    "requestDate": "2015-11-14",
    "slaPriority": 1,
    "responseDeadline": "2016-06-20",
    "responseDate": "2015-02-02",
    "status": "SUCCESS",
    "failureCode": "failure +0"
  },
  {
    "demandRid": "5b891dac3d8b65ffacdeae56",
    "meterMRID": "5b89180be32a0233adbccaa8",
    "serviceType": "1+undefined",
    "requestDate": "2018-06-06",
    "slaPriority": 1,
    "responseDeadline": "2017-04-09",
    "responseDate": "2017-10-10",
    "status": "OK",
    "failureCode": "failure +100"
  },
  {
    "demandRid": "5b891dacd5a0c0f064b8cfd8",
    "meterMRID": "5b89180bf90f9c23ffdbfc19",
    "serviceType": "1+undefined",
    "requestDate": "2014-10-23",
    "slaPriority": 1,
    "responseDeadline": "2018-03-19",
    "responseDate": "2016-09-23",
    "status": "OK",
    "failureCode": "failure +0"
  },
  {
    "demandRid": "5b891dac461a8e8a9c319dd1",
    "meterMRID": "5b89180b815a237d25269971",
    "serviceType": "1+undefined",
    "requestDate": "2014-06-28",
    "slaPriority": 27,
    "responseDeadline": "2016-07-08",
    "responseDate": "2017-05-27",
    "status": "FAIL",
    "failureCode": "failure +0"
  },
  {
    "demandRid": "5b891dac038bd1bea075ac14",
    "meterMRID": "5b89180b6ec7a3373fdc8dcd",
    "serviceType": "1+undefined",
    "requestDate": "2017-06-05",
    "slaPriority": 1,
    "responseDeadline": "2017-05-31",
    "responseDate": "2015-12-31",
    "status": "SUCCESS",
    "failureCode": "failure +100"
  },
  {
    "demandRid": "5b891dac2972772db291e5fc",
    "meterMRID": "5b89180b6ec7a3373fdc8dcd",
    "serviceType": "1+undefined",
    "requestDate": "2015-01-21",
    "slaPriority": 27,
    "responseDeadline": "2014-08-26",
    "responseDate": "2015-07-20",
    "status": "SUCCESS",
    "failureCode": "failure +100"
  },
  {
    "demandRid": "5b891dac4324efcdc67b7ca2",
    "meterMRID": "5b89180b4ffa88ba3d210819",
    "serviceType": "1+undefined",
    "requestDate": "2014-08-10",
    "slaPriority": 1,
    "responseDeadline": "2016-11-19",
    "responseDate": "2016-07-05",
    "status": "FAIL",
    "failureCode": "failure +100"
  },
  {
    "demandRid": "5b891dac3e07c392b0ed3c08",
    "meterMRID": "5b89180ba15bb86b9d0d91cd",
    "serviceType": "1+undefined",
    "requestDate": "2015-08-06",
    "slaPriority": 9,
    "responseDeadline": "2014-09-14",
    "responseDate": "2016-06-26",
    "status": "OK",
    "failureCode": "failure +0"
  },
  {
    "demandRid": "5b891dacf2258d5c3bb88bc4",
    "meterMRID": "5b89180b54f5139639a2cbd7",
    "serviceType": "1+undefined",
    "requestDate": "2017-02-06",
    "slaPriority": 27,
    "responseDeadline": "2016-08-26",
    "responseDate": "2016-08-25",
    "status": "SUCCESS",
    "failureCode": "failure +100"
  },
  {
    "demandRid": "5b891dac6f3132df2c72547b",
    "meterMRID": "5b89180b54f5139639a2cbd7",
    "serviceType": "1+undefined",
    "requestDate": "2017-11-30",
    "slaPriority": 1,
    "responseDeadline": "2017-08-03",
    "responseDate": "2017-06-30",
    "status": "FAIL",
    "failureCode": "failure +100"
  },
  {
    "demandRid": "5b891dac8a0fda2c997be3d4",
    "meterMRID": "5b89180b815a237d25269971",
    "serviceType": "1+undefined",
    "requestDate": "2018-07-15",
    "slaPriority": 27,
    "responseDeadline": "2016-01-27",
    "responseDate": "2015-03-26",
    "status": "FAIL",
    "failureCode": "failure +0"
  },
  {
    "demandRid": "5b891dacf267b4a4c055c537",
    "meterMRID": "5b89180bf90f9c23ffdbfc19",
    "serviceType": "1+undefined",
    "requestDate": "2016-12-07",
    "slaPriority": 9,
    "responseDeadline": "2018-08-27",
    "responseDate": "2016-08-05",
    "status": "OK",
    "failureCode": "failure +100"
  },
  {
    "demandRid": "5b891dac2840d7bfae75ef0e",
    "meterMRID": "5b89180b54f5139639a2cbd7",
    "serviceType": "1+undefined",
    "requestDate": "2014-05-26",
    "slaPriority": 9,
    "responseDeadline": "2014-09-08",
    "responseDate": "2014-07-28",
    "status": "SUCCESS",
    "failureCode": "failure +100"
  },
  {
    "demandRid": "5b891dacee5464957df14b02",
    "meterMRID": "5b89180b4dea33c30a1d4949",
    "serviceType": "1+undefined",
    "requestDate": "2018-07-29",
    "slaPriority": 9,
    "responseDeadline": "2015-03-29",
    "responseDate": "2015-05-04",
    "status": "OK",
    "failureCode": "failure +100"
  },
  {
    "demandRid": "5b891dac277dcb4ef5c597c1",
    "meterMRID": "5b89180b4ffa88ba3d210819",
    "serviceType": "1+undefined",
    "requestDate": "2014-03-16",
    "slaPriority": 27,
    "responseDeadline": "2014-12-14",
    "responseDate": "2015-08-17",
    "status": "SUCCESS",
    "failureCode": "failure +100"
  },
  {
    "demandRid": "5b891dacd0c1db69626047a7",
    "meterMRID": "5b89180b4ffa88ba3d210819",
    "serviceType": "1+undefined",
    "requestDate": "2018-02-12",
    "slaPriority": 9,
    "responseDeadline": "2017-02-18",
    "responseDate": "2017-01-18",
    "status": "SUCCESS",
    "failureCode": "failure +0"
  },
  {
    "demandRid": "5b891dacd6383ee11ae2a15a",
    "meterMRID": "5b89180b7c8e476e6fd2690f",
    "serviceType": "1+undefined",
    "requestDate": "2016-10-08",
    "slaPriority": 9,
    "responseDeadline": "2016-03-25",
    "responseDate": "2015-07-22",
    "status": "SUCCESS",
    "failureCode": "failure +100"
  },
  {
    "demandRid": "5b891dacde42b09c8b154f68",
    "meterMRID": "5b89180b4dea33c30a1d4949",
    "serviceType": "1+undefined",
    "requestDate": "2016-08-03",
    "slaPriority": 27,
    "responseDeadline": "2017-06-01",
    "responseDate": "2015-08-22",
    "status": "OK",
    "failureCode": "failure +100"
  },
  {
    "demandRid": "5b891dacbf83bc0d47635d3f",
    "meterMRID": "5b89180be32a0233adbccaa8",
    "serviceType": "1+undefined",
    "requestDate": "2014-09-26",
    "slaPriority": 27,
    "responseDeadline": "2016-05-01",
    "responseDate": "2016-05-08",
    "status": "OK",
    "failureCode": "failure +100"
  },
  {
    "demandRid": "5b891dacda4c491793f36434",
    "meterMRID": "5b89180b4ffa88ba3d210819",
    "serviceType": "1+undefined",
    "requestDate": "2016-04-01",
    "slaPriority": 1,
    "responseDeadline": "2017-10-10",
    "responseDate": "2016-07-08",
    "status": "OK",
    "failureCode": "failure +100"
  },
  {
    "demandRid": "5b891dacf72808d75b7880eb",
    "meterMRID": "5b89180b4ffa88ba3d210819",
    "serviceType": "1+undefined",
    "requestDate": "2018-07-12",
    "slaPriority": 27,
    "responseDeadline": "2015-09-24",
    "responseDate": "2015-01-20",
    "status": "SUCCESS",
    "failureCode": "failure +0"
  },
  {
    "demandRid": "5b891dac942b4a6c36c1946d",
    "meterMRID": "5b89180b815a237d25269971",
    "serviceType": "1+undefined",
    "requestDate": "2018-07-27",
    "slaPriority": 27,
    "responseDeadline": "2014-09-13",
    "responseDate": "2015-07-12",
    "status": "OK",
    "failureCode": "failure +100"
  },
  {
    "demandRid": "5b891dac3e4afbfc38a26fda",
    "meterMRID": "5b89180b815a237d25269971",
    "serviceType": "1+undefined",
    "requestDate": "2016-03-03",
    "slaPriority": 9,
    "responseDeadline": "2016-01-07",
    "responseDate": "2018-06-29",
    "status": "OK",
    "failureCode": "failure +100"
  },
  {
    "demandRid": "5b891dace840827e0d953219",
    "meterMRID": "5b89180b6ec7a3373fdc8dcd",
    "serviceType": "1+undefined",
    "requestDate": "2016-05-11",
    "slaPriority": 1,
    "responseDeadline": "2015-10-17",
    "responseDate": "2016-04-26",
    "status": "OK",
    "failureCode": "failure +0"
  },
  {
    "demandRid": "5b891dac8de24c256601a993",
    "meterMRID": "5b89180bf90f9c23ffdbfc19",
    "serviceType": "1+undefined",
    "requestDate": "2016-12-22",
    "slaPriority": 27,
    "responseDeadline": "2017-11-23",
    "responseDate": "2017-05-21",
    "status": "SUCCESS",
    "failureCode": "failure +100"
  },
  {
    "demandRid": "5b891dac53df7f537d1764f7",
    "meterMRID": "5b89180b815a237d25269971",
    "serviceType": "1+undefined",
    "requestDate": "2018-02-13",
    "slaPriority": 27,
    "responseDeadline": "2016-02-05",
    "responseDate": "2015-10-07",
    "status": "SUCCESS",
    "failureCode": "failure +100"
  },
  {
    "demandRid": "5b891dac23128135c833fb3c",
    "meterMRID": "5b89180b6ec7a3373fdc8dcd",
    "serviceType": "1+undefined",
    "requestDate": "2014-10-31",
    "slaPriority": 1,
    "responseDeadline": "2014-02-21",
    "responseDate": "2015-04-24",
    "status": "SUCCESS",
    "failureCode": "failure +0"
  },
  {
    "demandRid": "5b891dacd416f92925a633d6",
    "meterMRID": "5b89180be32a0233adbccaa8",
    "serviceType": "1+undefined",
    "requestDate": "2018-02-06",
    "slaPriority": 9,
    "responseDeadline": "2017-07-08",
    "responseDate": "2018-01-22",
    "status": "SUCCESS",
    "failureCode": "failure +0"
  },
  {
    "demandRid": "5b891dacb1118467567506df",
    "meterMRID": "5b89180b44c660797d20b1bd",
    "serviceType": "1+undefined",
    "requestDate": "2015-02-04",
    "slaPriority": 9,
    "responseDeadline": "2016-03-30",
    "responseDate": "2014-10-10",
    "status": "FAIL",
    "failureCode": "failure +0"
  },
  {
    "demandRid": "5b891dac4d78521de17455f1",
    "meterMRID": "5b89180bf90f9c23ffdbfc19",
    "serviceType": "1+undefined",
    "requestDate": "2015-07-12",
    "slaPriority": 27,
    "responseDeadline": "2015-03-12",
    "responseDate": "2015-05-12",
    "status": "OK",
    "failureCode": "failure +0"
  },
  {
    "demandRid": "5b891dac9cba56825b3c1e9e",
    "meterMRID": "5b89180b4ffa88ba3d210819",
    "serviceType": "1+undefined",
    "requestDate": "2017-05-02",
    "slaPriority": 1,
    "responseDeadline": "2015-12-16",
    "responseDate": "2017-02-09",
    "status": "FAIL",
    "failureCode": "failure +0"
  },
  {
    "demandRid": "5b891dacd43708ff5c1433b9",
    "meterMRID": "5b89180b815a237d25269971",
    "serviceType": "1+undefined",
    "requestDate": "2016-11-15",
    "slaPriority": 27,
    "responseDeadline": "2018-03-17",
    "responseDate": "2017-04-09",
    "status": "FAIL",
    "failureCode": "failure +100"
  },
  {
    "demandRid": "5b891dac6bf7af4332167ca2",
    "meterMRID": "5b89180b6ec7a3373fdc8dcd",
    "serviceType": "1+undefined",
    "requestDate": "2018-07-01",
    "slaPriority": 27,
    "responseDeadline": "2018-05-31",
    "responseDate": "2018-08-20",
    "status": "SUCCESS",
    "failureCode": "failure +100"
  },
  {
    "demandRid": "5b891dac6823074deae6d88d",
    "meterMRID": "5b89180b44c660797d20b1bd",
    "serviceType": "1+undefined",
    "requestDate": "2017-01-02",
    "slaPriority": 27,
    "responseDeadline": "2014-07-07",
    "responseDate": "2014-11-03",
    "status": "FAIL",
    "failureCode": "failure +100"
  },
  {
    "demandRid": "5b891dac7e9e0c53d81cd517",
    "meterMRID": "5b89180bf90f9c23ffdbfc19",
    "serviceType": "1+undefined",
    "requestDate": "2017-02-27",
    "slaPriority": 1,
    "responseDeadline": "2016-05-20",
    "responseDate": "2017-01-26",
    "status": "SUCCESS",
    "failureCode": "failure +100"
  },
  {
    "demandRid": "5b891dac328b8f60bb9536ba",
    "meterMRID": "5b89180b7c8e476e6fd2690f",
    "serviceType": "1+undefined",
    "requestDate": "2014-12-22",
    "slaPriority": 1,
    "responseDeadline": "2015-08-24",
    "responseDate": "2018-08-05",
    "status": "SUCCESS",
    "failureCode": "failure +0"
  },
  {
    "demandRid": "5b891dacffe9f0760770e657",
    "meterMRID": "5b89180ba15bb86b9d0d91cd",
    "serviceType": "1+undefined",
    "requestDate": "2015-01-21",
    "slaPriority": 1,
    "responseDeadline": "2017-10-10",
    "responseDate": "2017-11-22",
    "status": "SUCCESS",
    "failureCode": "failure +100"
  },
  {
    "demandRid": "5b891dacc1344ceecc13ed3d",
    "meterMRID": "5b89180b815a237d25269971",
    "serviceType": "1+undefined",
    "requestDate": "2017-01-24",
    "slaPriority": 27,
    "responseDeadline": "2015-05-25",
    "responseDate": "2015-03-28",
    "status": "OK",
    "failureCode": "failure +0"
  },
  {
    "demandRid": "5b891dac87e988fc20977556",
    "meterMRID": "5b89180b4dea33c30a1d4949",
    "serviceType": "1+undefined",
    "requestDate": "2015-10-07",
    "slaPriority": 1,
    "responseDeadline": "2015-02-23",
    "responseDate": "2014-01-25",
    "status": "FAIL",
    "failureCode": "failure +100"
  },
  {
    "demandRid": "5b891dac2dc7ef2fd7ccde68",
    "meterMRID": "5b89180b4dea33c30a1d4949",
    "serviceType": "1+undefined",
    "requestDate": "2017-01-28",
    "slaPriority": 9,
    "responseDeadline": "2016-12-06",
    "responseDate": "2015-01-04",
    "status": "OK",
    "failureCode": "failure +100"
  },
  {
    "demandRid": "5b891dacda1435ea26d956e2",
    "meterMRID": "5b89180b4dea33c30a1d4949",
    "serviceType": "1+undefined",
    "requestDate": "2014-08-10",
    "slaPriority": 9,
    "responseDeadline": "2015-07-04",
    "responseDate": "2015-07-02",
    "status": "SUCCESS",
    "failureCode": "failure +100"
  },
  {
    "demandRid": "5b891dac5ceb0f0bc912f9ea",
    "meterMRID": "5b89180b6ec7a3373fdc8dcd",
    "serviceType": "1+undefined",
    "requestDate": "2014-06-11",
    "slaPriority": 27,
    "responseDeadline": "2014-12-30",
    "responseDate": "2016-01-24",
    "status": "SUCCESS",
    "failureCode": "failure +100"
  },
  {
    "demandRid": "5b891dace4a140c9b93a9f4a",
    "meterMRID": "5b89180be32a0233adbccaa8",
    "serviceType": "1+undefined",
    "requestDate": "2016-08-29",
    "slaPriority": 1,
    "responseDeadline": "2017-10-21",
    "responseDate": "2017-05-03",
    "status": "SUCCESS",
    "failureCode": "failure +100"
  },
  {
    "demandRid": "5b891dacefbdd7a9e53a96a2",
    "meterMRID": "5b89180b54f5139639a2cbd7",
    "serviceType": "1+undefined",
    "requestDate": "2015-09-11",
    "slaPriority": 27,
    "responseDeadline": "2015-07-16",
    "responseDate": "2015-05-19",
    "status": "FAIL",
    "failureCode": "failure +0"
  },
  {
    "demandRid": "5b891dac00e1d3db8471b2a6",
    "meterMRID": "5b89180b815a237d25269971",
    "serviceType": "1+undefined",
    "requestDate": "2015-02-04",
    "slaPriority": 27,
    "responseDeadline": "2018-01-03",
    "responseDate": "2017-11-02",
    "status": "OK",
    "failureCode": "failure +100"
  },
  {
    "demandRid": "5b891dacbda91ac5978d83f8",
    "meterMRID": "5b89180b6ec7a3373fdc8dcd",
    "serviceType": "1+undefined",
    "requestDate": "2018-01-10",
    "slaPriority": 27,
    "responseDeadline": "2017-12-05",
    "responseDate": "2016-05-07",
    "status": "SUCCESS",
    "failureCode": "failure +0"
  },
  {
    "demandRid": "5b891dac8a3f8cd2c722f4db",
    "meterMRID": "5b89180b815a237d25269971",
    "serviceType": "1+undefined",
    "requestDate": "2014-02-13",
    "slaPriority": 1,
    "responseDeadline": "2014-11-04",
    "responseDate": "2016-03-01",
    "status": "OK",
    "failureCode": "failure +100"
  },
  {
    "demandRid": "5b891dacb699c0a3a4f67fee",
    "meterMRID": "5b89180b44c660797d20b1bd",
    "serviceType": "1+undefined",
    "requestDate": "2014-10-08",
    "slaPriority": 1,
    "responseDeadline": "2015-09-30",
    "responseDate": "2016-10-03",
    "status": "OK",
    "failureCode": "failure +100"
  },
  {
    "demandRid": "5b891dac72f09ba566f11044",
    "meterMRID": "5b89180b54f5139639a2cbd7",
    "serviceType": "1+undefined",
    "requestDate": "2016-11-23",
    "slaPriority": 9,
    "responseDeadline": "2014-04-18",
    "responseDate": "2014-07-05",
    "status": "SUCCESS",
    "failureCode": "failure +0"
  },
  {
    "demandRid": "5b891dac5fa63396ae3c976e",
    "meterMRID": "5b89180b4dea33c30a1d4949",
    "serviceType": "1+undefined",
    "requestDate": "2014-02-26",
    "slaPriority": 9,
    "responseDeadline": "2016-08-30",
    "responseDate": "2016-06-10",
    "status": "FAIL",
    "failureCode": "failure +0"
  },
  {
    "demandRid": "5b891dac5ed15849110b0238",
    "meterMRID": "5b89180b4ffa88ba3d210819",
    "serviceType": "1+undefined",
    "requestDate": "2015-04-21",
    "slaPriority": 1,
    "responseDeadline": "2015-05-27",
    "responseDate": "2018-03-27",
    "status": "FAIL",
    "failureCode": "failure +0"
  },
  {
    "demandRid": "5b891dacc7906cd2e3864eb7",
    "meterMRID": "5b89180ba15bb86b9d0d91cd",
    "serviceType": "1+undefined",
    "requestDate": "2014-06-25",
    "slaPriority": 9,
    "responseDeadline": "2014-05-13",
    "responseDate": "2014-03-19",
    "status": "SUCCESS",
    "failureCode": "failure +0"
  },
  {
    "demandRid": "5b891dac7d7cd8bdf7cc71a5",
    "meterMRID": "5b89180b54f5139639a2cbd7",
    "serviceType": "1+undefined",
    "requestDate": "2015-10-24",
    "slaPriority": 1,
    "responseDeadline": "2015-05-10",
    "responseDate": "2017-02-27",
    "status": "OK",
    "failureCode": "failure +0"
  },
  {
    "demandRid": "5b891dac4f34b19101b4cec4",
    "meterMRID": "5b89180b4dea33c30a1d4949",
    "serviceType": "1+undefined",
    "requestDate": "2014-04-09",
    "slaPriority": 9,
    "responseDeadline": "2018-04-24",
    "responseDate": "2016-11-28",
    "status": "FAIL",
    "failureCode": "failure +100"
  },
  {
    "demandRid": "5b891dac045fe87c1bc79f9e",
    "meterMRID": "5b89180be32a0233adbccaa8",
    "serviceType": "1+undefined",
    "requestDate": "2016-11-03",
    "slaPriority": 1,
    "responseDeadline": "2016-09-18",
    "responseDate": "2014-11-05",
    "status": "FAIL",
    "failureCode": "failure +0"
  },
  {
    "demandRid": "5b891dac94123b132be80b68",
    "meterMRID": "5b89180b44c660797d20b1bd",
    "serviceType": "1+undefined",
    "requestDate": "2015-05-21",
    "slaPriority": 27,
    "responseDeadline": "2016-07-02",
    "responseDate": "2015-02-14",
    "status": "OK",
    "failureCode": "failure +100"
  },
  {
    "demandRid": "5b891dacef44806be3b740d9",
    "meterMRID": "5b89180bf90f9c23ffdbfc19",
    "serviceType": "1+undefined",
    "requestDate": "2016-09-02",
    "slaPriority": 1,
    "responseDeadline": "2015-02-12",
    "responseDate": "2018-03-01",
    "status": "OK",
    "failureCode": "failure +100"
  },
  {
    "demandRid": "5b891dacc59017585841f8ff",
    "meterMRID": "5b89180b44c660797d20b1bd",
    "serviceType": "1+undefined",
    "requestDate": "2014-12-21",
    "slaPriority": 27,
    "responseDeadline": "2017-01-02",
    "responseDate": "2018-05-20",
    "status": "FAIL",
    "failureCode": "failure +0"
  },
  {
    "demandRid": "5b891dacd5352b4b61b811b2",
    "meterMRID": "5b89180bf90f9c23ffdbfc19",
    "serviceType": "1+undefined",
    "requestDate": "2016-12-21",
    "slaPriority": 9,
    "responseDeadline": "2017-10-25",
    "responseDate": "2016-05-01",
    "status": "FAIL",
    "failureCode": "failure +100"
  },
  {
    "demandRid": "5b891dac56a61f7997407875",
    "meterMRID": "5b89180b6ec7a3373fdc8dcd",
    "serviceType": "1+undefined",
    "requestDate": "2017-04-05",
    "slaPriority": 9,
    "responseDeadline": "2015-08-09",
    "responseDate": "2014-11-24",
    "status": "SUCCESS",
    "failureCode": "failure +100"
  },
  {
    "demandRid": "5b891dacadf334981b928c9f",
    "meterMRID": "5b89180b6ec7a3373fdc8dcd",
    "serviceType": "1+undefined",
    "requestDate": "2015-03-09",
    "slaPriority": 27,
    "responseDeadline": "2014-10-28",
    "responseDate": "2017-10-25",
    "status": "OK",
    "failureCode": "failure +100"
  },
  {
    "demandRid": "5b891dac4bda11f1d9a357c7",
    "meterMRID": "5b89180b815a237d25269971",
    "serviceType": "1+undefined",
    "requestDate": "2015-05-14",
    "slaPriority": 9,
    "responseDeadline": "2018-06-06",
    "responseDate": "2014-09-15",
    "status": "OK",
    "failureCode": "failure +0"
  },
  {
    "demandRid": "5b891dac57eb653203c3dcf6",
    "meterMRID": "5b89180b44c660797d20b1bd",
    "serviceType": "1+undefined",
    "requestDate": "2016-08-26",
    "slaPriority": 27,
    "responseDeadline": "2014-12-17",
    "responseDate": "2018-04-02",
    "status": "SUCCESS",
    "failureCode": "failure +0"
  },
  {
    "demandRid": "5b891dac86f651926c507462",
    "meterMRID": "5b89180be32a0233adbccaa8",
    "serviceType": "1+undefined",
    "requestDate": "2018-05-01",
    "slaPriority": 27,
    "responseDeadline": "2014-06-04",
    "responseDate": "2015-04-21",
    "status": "SUCCESS",
    "failureCode": "failure +100"
  },
  {
    "demandRid": "5b891dac47321dd043d5e315",
    "meterMRID": "5b89180b44c660797d20b1bd",
    "serviceType": "1+undefined",
    "requestDate": "2016-04-20",
    "slaPriority": 27,
    "responseDeadline": "2014-06-02",
    "responseDate": "2015-04-03",
    "status": "FAIL",
    "failureCode": "failure +100"
  },
  {
    "demandRid": "5b891dac609e7dfcd7fa7b7a",
    "meterMRID": "5b89180be32a0233adbccaa8",
    "serviceType": "1+undefined",
    "requestDate": "2017-02-14",
    "slaPriority": 9,
    "responseDeadline": "2014-11-23",
    "responseDate": "2017-08-11",
    "status": "SUCCESS",
    "failureCode": "failure +0"
  },
  {
    "demandRid": "5b891dac0e80eeb52e18ef62",
    "meterMRID": "5b89180ba15bb86b9d0d91cd",
    "serviceType": "1+undefined",
    "requestDate": "2015-07-07",
    "slaPriority": 1,
    "responseDeadline": "2017-09-30",
    "responseDate": "2016-08-24",
    "status": "OK",
    "failureCode": "failure +100"
  },
  {
    "demandRid": "5b891dacefebb542e9e1d20c",
    "meterMRID": "5b89180bf90f9c23ffdbfc19",
    "serviceType": "1+undefined",
    "requestDate": "2018-08-26",
    "slaPriority": 1,
    "responseDeadline": "2014-04-24",
    "responseDate": "2017-02-10",
    "status": "FAIL",
    "failureCode": "failure +0"
  },
  {
    "demandRid": "5b891dacaff2cb2efb3b3d43",
    "meterMRID": "5b89180b4dea33c30a1d4949",
    "serviceType": "1+undefined",
    "requestDate": "2016-07-21",
    "slaPriority": 9,
    "responseDeadline": "2016-07-24",
    "responseDate": "2015-07-11",
    "status": "FAIL",
    "failureCode": "failure +0"
  },
  {
    "demandRid": "5b891daca497d3c3ee5c9cb3",
    "meterMRID": "5b89180b4ffa88ba3d210819",
    "serviceType": "1+undefined",
    "requestDate": "2018-04-17",
    "slaPriority": 9,
    "responseDeadline": "2017-03-13",
    "responseDate": "2017-02-28",
    "status": "OK",
    "failureCode": "failure +0"
  },
  {
    "demandRid": "5b891dace057b48461a1648f",
    "meterMRID": "5b89180b44c660797d20b1bd",
    "serviceType": "1+undefined",
    "requestDate": "2017-07-20",
    "slaPriority": 27,
    "responseDeadline": "2016-12-16",
    "responseDate": "2017-02-23",
    "status": "FAIL",
    "failureCode": "failure +100"
  },
  {
    "demandRid": "5b891dace7da54cbdbd222bf",
    "meterMRID": "5b89180b4ffa88ba3d210819",
    "serviceType": "1+undefined",
    "requestDate": "2017-10-02",
    "slaPriority": 27,
    "responseDeadline": "2018-06-17",
    "responseDate": "2015-12-07",
    "status": "SUCCESS",
    "failureCode": "failure +100"
  },
  {
    "demandRid": "5b891dac1d6c6df9ccb26d51",
    "meterMRID": "5b89180ba15bb86b9d0d91cd",
    "serviceType": "1+undefined",
    "requestDate": "2018-07-09",
    "slaPriority": 27,
    "responseDeadline": "2017-04-28",
    "responseDate": "2016-10-30",
    "status": "SUCCESS",
    "failureCode": "failure +0"
  },
  {
    "demandRid": "5b891dac8ff9dd4c6a798359",
    "meterMRID": "5b89180b4dea33c30a1d4949",
    "serviceType": "1+undefined",
    "requestDate": "2014-09-30",
    "slaPriority": 27,
    "responseDeadline": "2014-12-06",
    "responseDate": "2014-05-03",
    "status": "SUCCESS",
    "failureCode": "failure +0"
  },
  {
    "demandRid": "5b891dac181d7d374d5fb527",
    "meterMRID": "5b89180ba15bb86b9d0d91cd",
    "serviceType": "1+undefined",
    "requestDate": "2015-09-12",
    "slaPriority": 9,
    "responseDeadline": "2015-02-18",
    "responseDate": "2017-09-11",
    "status": "OK",
    "failureCode": "failure +100"
  },
  {
    "demandRid": "5b891dacc71b55446bc48e3f",
    "meterMRID": "5b89180bf90f9c23ffdbfc19",
    "serviceType": "1+undefined",
    "requestDate": "2015-03-01",
    "slaPriority": 27,
    "responseDeadline": "2016-11-26",
    "responseDate": "2017-03-31",
    "status": "SUCCESS",
    "failureCode": "failure +100"
  },
  {
    "demandRid": "5b891dac60604b4cd825ef11",
    "meterMRID": "5b89180ba15bb86b9d0d91cd",
    "serviceType": "1+undefined",
    "requestDate": "2017-07-23",
    "slaPriority": 9,
    "responseDeadline": "2017-06-17",
    "responseDate": "2018-02-18",
    "status": "OK",
    "failureCode": "failure +100"
  },
  {
    "demandRid": "5b891dacd597ca47a0ecd78e",
    "meterMRID": "5b89180bf90f9c23ffdbfc19",
    "serviceType": "1+undefined",
    "requestDate": "2017-01-31",
    "slaPriority": 1,
    "responseDeadline": "2017-12-16",
    "responseDate": "2016-07-05",
    "status": "FAIL",
    "failureCode": "failure +100"
  },
  {
    "demandRid": "5b891dac0daeac549c2f88df",
    "meterMRID": "5b89180ba15bb86b9d0d91cd",
    "serviceType": "1+undefined",
    "requestDate": "2018-05-10",
    "slaPriority": 27,
    "responseDeadline": "2017-09-27",
    "responseDate": "2015-06-30",
    "status": "OK",
    "failureCode": "failure +0"
  },
  {
    "demandRid": "5b891dace28e3649772b484d",
    "meterMRID": "5b89180b54f5139639a2cbd7",
    "serviceType": "1+undefined",
    "requestDate": "2016-11-26",
    "slaPriority": 9,
    "responseDeadline": "2017-04-10",
    "responseDate": "2014-04-15",
    "status": "FAIL",
    "failureCode": "failure +100"
  }
]